lambdev/__init__.py
lambdev/aws_lambda.py
lambdev/core.py
lambdev-0.1.2.dist-info/LICENSE
lambdev-0.1.2.dist-info/METADATA
lambdev-0.1.2.dist-info/WHEEL
lambdev-0.1.2.dist-info/top_level.txt
lambdev-0.1.2.dist-info/RECORD
